streamlit_custom_input/__init__.py
streamlit_custom_input/frontend/build/asset-manifest.json
streamlit_custom_input/frontend/build/bootstrap.min.css
streamlit_custom_input/frontend/build/index.html
streamlit_custom_input/frontend/build/input_example.png
streamlit_custom_input/frontend/build/send.png
streamlit_custom_input/frontend/build/static/css/main.241951ba.css
streamlit_custom_input/frontend/build/static/css/main.241951ba.css.map
streamlit_custom_input/frontend/build/static/js/main.9cbae9fd.js
streamlit_custom_input/frontend/build/static/js/main.9cbae9fd.js.LICENSE.txt
streamlit_custom_input/frontend/build/static/js/main.9cbae9fd.js.map
streamlit_custom_input-0.1.0.dist-info/LICENSE
streamlit_custom_input-0.1.0.dist-info/METADATA
streamlit_custom_input-0.1.0.dist-info/WHEEL
streamlit_custom_input-0.1.0.dist-info/top_level.txt
streamlit_custom_input-0.1.0.dist-info/RECORD
